bioio_types/__init__.py
bioio_types/constants.py
bioio_types/dimensions.py
bioio_types/exceptions.py
bioio_types/image_container.py
bioio_types/io.py
bioio_types/py.typed
bioio_types/reader.py
bioio_types/reader_metadata.py
bioio_types/transforms.py
bioio_types/types.py
bioio_types/tests/conftest.py
bioio_types/tests/test_empty.py
docs/conf.py
docs/contributing.rst
docs/index.rst
docs/installation.rst
bioio_types-0.0.2.dist-info/LICENSE
bioio_types-0.0.2.dist-info/METADATA
bioio_types-0.0.2.dist-info/WHEEL
bioio_types-0.0.2.dist-info/top_level.txt
bioio_types-0.0.2.dist-info/RECORD
